0     LOAD_CONST              'aaaaaa'
1     LOAD_NAME               k
2     STORE
3     LOAD_NAME               k
4     LOAD_NAME               d
5     PUSH_SCOPE
6     BIND_ADDR               to_print
7     BIND_ADDR               kek
8     CALL_SUBPROGRAM         27 (2)
9     POP_SCOPE
10    LABEL                   call_declaration_label_10
11    LOAD_CONST              'after: '
12    LOAD_NAME               k
13    DEREFERENCE
14    CALL_FUNCTION           Print (2)
15    LOAD_CONST              'after: '
16    LOAD_NAME               d
17    DEREFERENCE
18    CALL_FUNCTION           Print (2)
19    HALT
20    LABEL                   print
21    LOAD_CONST              Null
22    LOAD_NAME               to_print
23    STORE
24    LOAD_CONST              Null
25    LOAD_NAME               kek
26    STORE
27    LOAD_CONST              'inside: '
28    LOAD_NAME               to_print
29    DEREFERENCE
30    CALL_FUNCTION           Print (2)
31    LOAD_CONST              'ddddd'
32    LOAD_NAME               to_print
33    STORE
34    LOAD_CONST              'pprprp'
35    LOAD_NAME               kek
36    STORE
37    RETURN_VALUE
